setup.py
learnusumjap/__init__.py
learnusumjap/explain_reading.py
learnusumjap/explain_reading_db.py
learnusumjap/explain_reading_example.py
learnusumjap/jmdict.py
learnusumjap/kanji_word_examples.py
learnusumjap/mora.py
learnusumjap/re_one_of.py
learnusumjap/unicode.py
learnusumjap.egg-info/PKG-INFO
learnusumjap.egg-info/SOURCES.txt
learnusumjap.egg-info/dependency_links.txt
learnusumjap.egg-info/requires.txt
learnusumjap.egg-info/top_level.txt