Metadata-Version: 1.1
Name: learnusumjap
Version: 0.1.15
Summary: Japanese language utilities
Home-page: https://hydra.bacontoast.org/f/learnusumjap/
Author: jikan@cock.li
Author-email: jikan@cock.li
License: LGPLv3
Platform: UNKNOWN
Classifier: Programming Language :: Python :: 3 :: Only
